README.rst
setup.py
persizmq/__init__.py
persizmq/filter.py
persizmq/py.typed
persizmq.egg-info/PKG-INFO
persizmq.egg-info/SOURCES.txt
persizmq.egg-info/dependency_links.txt
persizmq.egg-info/requires.txt
persizmq.egg-info/top_level.txt